{
  "$ref": "#/$defs/type-12",
  "$defs": {
    "type-1": {
      "anyOf": [
        {
          "type": "string",
          "const": "module"
        },
        {
          "type": "string",
          "const": "commonjs"
        }
      ]
    },
    "type-2": {
      "anyOf": [
        {
          "type": "string",
          "const": "Apache-2.0"
        },
        {
          "type": "string",
          "const": "BSD-2-Clause"
        },
        {
          "type": "string",
          "const": "BSD-3-Clause"
        },
        {
          "type": "string",
          "const": "ISC"
        },
        {
          "type": "string",
          "const": "MIT"
        },
        {
          "type": "string",
          "const": "MPL-2.0"
        },
        {
          "type": "string",
          "const": "Unlicense"
        },
        {
          "type": "string",
          "const": "WTFPL"
        }
      ]
    },
    "type-3": {
      "type": "object",
      "required": [],
      "properties": {
        "npm": {
          "type": "boolean"
        },
        "repo": {
          "type": "boolean"
        },
        "coverage": {
          "type": "boolean"
        },
        "license": {
          "type": "boolean"
        },
        "discord": {
          "type": "string"
        }
      },
      "additionalProperties": false
    },
    "type-4": {
      "anyOf": [
        {
          "type": "string",
          "const": "pnpm"
        },
        {
          "type": "string",
          "const": "yarn"
        },
        {
          "type": "string",
          "const": "npm"
        }
      ]
    },
    "type-5": {
      "type": "object",
      "required": [
        "name"
      ],
      "properties": {
        "name": {
          "type": "string"
        },
        "type": {
          "$ref": "#/$defs/type-1"
        },
        "dir": {
          "type": "string",
          "description": "Directory name of this package, defaults to package name (\"@*/\" removed if any)."
        },
        "badges": {
          "$ref": "#/$defs/type-3"
        }
      },
      "additionalProperties": false
    },
    "type-6": {
      "type": "array",
      "items": {
        "$ref": "#/$defs/type-5"
      }
    },
    "type-7": {
      "anyOf": [
        {
          "type": "string",
          "const": "as-needed"
        },
        {
          "type": "string",
          "const": "consistent"
        },
        {
          "type": "string",
          "const": "preserve"
        }
      ]
    },
    "type-8": {
      "anyOf": [
        {
          "type": "string",
          "const": "es5"
        },
        {
          "type": "string",
          "const": "none"
        },
        {
          "type": "string",
          "const": "all"
        }
      ]
    },
    "type-9": {
      "anyOf": [
        {
          "type": "string",
          "const": "always"
        },
        {
          "type": "string",
          "const": "avoid"
        }
      ]
    },
    "type-10": {
      "type": "object",
      "required": [
        "printWidth",
        "tabWidth",
        "useTabs",
        "semi",
        "singleQuote",
        "quoteProps",
        "jsxSingleQuote",
        "trailingComma",
        "bracketSpacing",
        "bracketSameLine",
        "arrowParens"
      ],
      "properties": {
        "printWidth": {
          "type": "number"
        },
        "tabWidth": {
          "type": "number"
        },
        "useTabs": {
          "type": "boolean"
        },
        "semi": {
          "type": "boolean"
        },
        "singleQuote": {
          "type": "boolean"
        },
        "quoteProps": {
          "$ref": "#/$defs/type-7"
        },
        "jsxSingleQuote": {
          "type": "boolean"
        },
        "trailingComma": {
          "$ref": "#/$defs/type-8"
        },
        "bracketSpacing": {
          "type": "boolean"
        },
        "bracketSameLine": {
          "type": "boolean"
        },
        "arrowParens": {
          "$ref": "#/$defs/type-9"
        }
      },
      "additionalProperties": false
    },
    "type-11": {
      "type": "object",
      "required": [
        "name",
        "type",
        "defaultBranch",
        "packageManager"
      ],
      "properties": {
        "name": {
          "type": "string"
        },
        "type": {
          "$ref": "#/$defs/type-1"
        },
        "description": {
          "type": "string"
        },
        "repository": {
          "type": "string"
        },
        "license": {
          "$ref": "#/$defs/type-2"
        },
        "author": {
          "type": "string"
        },
        "badges": {
          "$ref": "#/$defs/type-3"
        },
        "defaultBranch": {
          "type": "string"
        },
        "packageManager": {
          "$ref": "#/$defs/type-4"
        },
        "packagesDir": {
          "type": "string",
          "description": "Name of the packages directory, defaults to \"packages\"."
        },
        "packages": {
          "$ref": "#/$defs/type-6"
        },
        "prettier": {
          "$ref": "#/$defs/type-10"
        }
      },
      "additionalProperties": false
    },
    "type-12": {
      "type": "object",
      "required": [
        "$schema",
        "boilerplate",
        "options"
      ],
      "properties": {
        "$schema": {
          "type": "string"
        },
        "boilerplate": {
          "type": "string"
        },
        "options": {
          "$ref": "#/$defs/type-11"
        }
      },
      "additionalProperties": false
    }
  }
}